nose_allure/__init__.py
nose_allure/utils.py
nose_allure_plugin-1.0.6.dist-info/METADATA
nose_allure_plugin-1.0.6.dist-info/WHEEL
nose_allure_plugin-1.0.6.dist-info/entry_points.txt
nose_allure_plugin-1.0.6.dist-info/top_level.txt
nose_allure_plugin-1.0.6.dist-info/RECORD
