Metadata-Version: 2.1
Name: nose-allure-plugin
Version: 1.0.6
Summary: Nose plugin for allure framework
Home-page: https://github.com/allure-framework/allure-nose-adaptor
Author: Sergey Chipiga
Author-email: chipiga86@gmail.com
License: UNKNOWN
Platform: UNKNOWN
Requires-Dist: nose
Requires-Dist: pytest-allure-adaptor
